{
    "modules": {
        "value": {
            "items": [
                {
                    "name": "sxa",
                    "templateLink": "https://raw.githubusercontent.com/Sitecore/Sitecore-Azure-Quickstart-Templates/master/SXA%201.3.1/xp/azuredeploy.json",
                    "parameters": {
                        "cdSxaMsDeployPackageUrl": "<URL of the WDP file Sitecore Experience Accelerator * CD.scwdp.zip>",
                        "cmSxaMsDeployPackageUrl": "<URL of the WDP file Sitecore Experience Accelerator *.scwdp.zip>",
                        "speMsDeployPackageUrl": "<URL of the WDP file Sitecore PowerShell Extensions *.scwdp.zip>"
                    }
                },
                {
                    "name": "def",
                    "templateLink": "<URL to the DEF json ARM template>",
                    "parameters": {
                        "defDeployPackageUrl": "<URL to the def module's WDP>",
                        "defSitecoreDeployPackageUrl": "<URL to the defSitecore module's WDP>",
                        "defSqlDeployPackageUrl": "<URL to the defSql module's WDP>",
                        "defxConnectDeployPackageUrl": "<URL to the defxConnect module's WDP>",
                        "defDynamicsDeployPackageUrl": "<URL to the defDynamics module's WDP>",
                        "defDynamicsConnectDeployPackageUrl": "<URL to the defDynamicsConnect module's WDP>",
                        "defSalesforceDeployPackageUrl": "<URL to the defDynamics module's WDP>",
                        "defSalesforceConnectDeployPackageUrl": "<URL to the defDynamicsConnect module's WDP>",
                        "defCdDeployPackageUrl": "<URL to the def-cd module's WDP>",
                        "defSitecoreCdDeployPackageUrl": "<URL to the defSitecore-cd module's WDP>",
                        "defSqlCdDeployPackageUrl": "<URL to the defSql-cd module's WDP>",
                        "defxConnectCdDeployPackageUrl": "<URL to the defxConnect-cd module's WDP>",
                        "defDynamicsCdDeployPackageUrl": "<URL to the defDynamics-cd module's WDP>",
                        "defDynamicsConnectCdDeployPackageUrl": "<URL to the defDynamicsConnect-cd module's WDP>",
                        "defSalesforceCdDeployPackageUrl": "<URL to the defDynamics-cd module's WDP>",
                        "defSalesforceConnectCdDeployPackageUrl": "<URL to the defDynamicsConnect-cd module's WDP>"
                    }
                },
                {
                    "name": "habitat-home-website",
                    "templateLink": "<URL to the Habitat Home json ARM template>",
                    "parameters": {
                        "habitatWebsiteCdMsDeployPackageUrl": "<URL to the Habitat Home WDP>",
                        "habitatWebsiteCmMsDeployPackageUrl": "<URL to the Habitat Home WDP>"
                    }
                },
                {
                    "name": "habitat-home-xc",
                    "templateLink": "<URL to the Habitat Home json ARM template>",
                    "parameters": {
                        "habitatXconnectDeployPackageUrl": "<URL to the Habitat Home XC WDP>"
                    }
                },
                {
                    "name": "bootloader",
                    "templateLink": "<URL to the bootloader template (Located in addons folder)>",
                    "parameters": {
                        "msDeployPackageUrl": "<URL to the wdp.zip file for specific version of Sitecore (Located in Sitecore Azure Toolkit\\resources\\SITECORE VERSION\\Addons)>"
                    }
                }
            ]
        }
    }
}